python2025_alexigna/__init__.py
python2025_alexigna/main.py
python2025_alexigna-0.1.1.dist-info/METADATA
python2025_alexigna-0.1.1.dist-info/WHEEL
python2025_alexigna-0.1.1.dist-info/RECORD
