Metadata-Version: 2.3
Name: python2025-alexigna
Version: 0.1.1
Summary: 
Author: alsigna
Author-email: ignatov.alx@gmail.com
Requires-Python: >=3.11
Classifier: Programming Language :: Python :: 3
Classifier: Programming Language :: Python :: 3.11
Classifier: Programming Language :: Python :: 3.12
Classifier: Programming Language :: Python :: 3.13
Requires-Dist: requests (>=2.32.4,<3.0.0)
